{
  "configVersion": 1,
  "index": "/multiselect/index.html",
  "assetGroups": [
    {
      "name": "app-shell",
      "installMode": "prefetch",
      "updateMode": "prefetch",
      "urls": [
        "/multiselect/index.html",
        "/multiselect/pwa-manifest.json"
      ],
      "patterns": [
        "https:\\/\\/fonts\\.googleapis\\.com\\/.*",
        "https:\\/\\/fonts\\.gstatic\\.com\\/s\\/.*",
        "https:\\/\\/maxcdn\\.bootstrapcdn\\.com\\/.*"
      ]
    },
    {
      "name": "assets-eager",
      "installMode": "prefetch",
      "updateMode": "prefetch",
      "urls": [],
      "patterns": []
    },
    {
      "name": "assets-lazy",
      "installMode": "lazy",
      "updateMode": "prefetch",
      "urls": [],
      "patterns": []
    },
    {
      "name": "docs-index",
      "installMode": "prefetch",
      "updateMode": "prefetch",
      "urls": [],
      "patterns": []
    },
    {
      "name": "docs-lazy",
      "installMode": "lazy",
      "updateMode": "lazy",
      "urls": [],
      "patterns": []
    }
  ],
  "dataGroups": [],
  "hashTable": {
    "/multiselect/index.html": "1e47433f2dce92c0bcbaa92f46e09d7a41ed88e7",
    "/multiselect/pwa-manifest.json": "ca71995127267c2c24cba2fc8a0054ae25c28f28"
  },
  "navigationUrls": [
    {
      "positive": true,
      "regex": "^\\/.*$"
    },
    {
      "positive": false,
      "regex": "^\\/(?:.+\\/)?[^/]*\\.[^/]*$"
    },
    {
      "positive": false,
      "regex": "^\\/(?:.+\\/)?[^/]*__[^/]*$"
    },
    {
      "positive": false,
      "regex": "^\\/(?:.+\\/)?[^/]*__[^/]*\\/.*$"
    }
  ]
}